{
	"song": {
		"player1": "bf",
		"player2": "wonder",
		"notes": [
			{
				"lengthInSteps": 16,
				"sectionNotes": [],
				"mustHitSection": true
			},
			{
				"lengthInSteps": 16,
				"sectionNotes": [],
				"mustHitSection": true
			},
			{
				"lengthInSteps": 16,
				"sectionNotes": [],
				"mustHitSection": true
			},
			{
				"lengthInSteps": 16,
				"sectionNotes": [],
				"mustHitSection": true
			},
			{
				"lengthInSteps": 16,
				"sectionNotes": [],
				"mustHitSection": true
			},
			{
				"lengthInSteps": 16,
				"sectionNotes": [],
				"mustHitSection": true
			},
			{
				"lengthInSteps": 16,
				"sectionNotes": [],
				"mustHitSection": true
			},
			{
				"lengthInSteps": 16,
				"sectionNotes": [
					[
						13381.2949640288,
						1,
						323.741007194245,
						0
					]
				],
				"mustHitSection": false
			},
			{
				"lengthInSteps": 16,
				"sectionNotes": [
					[
						13812.9496402878,
						2,
						755.395683453237,
						0
					],
					[
						14676.2589928058,
						1,
						755.395683453237,
						0
					]
				],
				"mustHitSection": false
			},
			{
				"lengthInSteps": 16,
				"sectionNotes": [
					[
						15539.5683453237,
						0,
						647.482014388489,
						0
					],
					[
						16726.618705036,
						0,
						215.827338129496,
						0
					],
					[
						16402.8776978417,
						1,
						0,
						0
					]
				],
				"mustHitSection": false
			},
			{
				"lengthInSteps": 16,
				"sectionNotes": [
					[
						17266.1870503597,
						1,
						1618.70503597122,
						0
					]
				],
				"mustHitSection": false
			},
			{
				"lengthInSteps": 16,
				"sectionNotes": [
					[
						20287.7697841727,
						1,
						323.741007194245,
						0
					]
				],
				"mustHitSection": true
			},
			{
				"lengthInSteps": 16,
				"sectionNotes": [
					[
						20719.4244604317,
						2,
						755.395683453237
					],
					[
						21582.7338129496,
						1,
						755.395683453237
					]
				],
				"mustHitSection": true
			},
			{
				"lengthInSteps": 16,
				"sectionNotes": [
					[
						22446.0431654676,
						0,
						647.482014388489
					],
					[
						23633.0935251799,
						0,
						215.827338129496
					],
					[
						23309.3525179856,
						1,
						0,
						0
					]
				],
				"mustHitSection": true
			},
			{
				"lengthInSteps": 16,
				"sectionNotes": [
					[
						24172.6618705036,
						2,
						755.395683453237,
						0
					],
					[
						25035.9712230216,
						0,
						539.568345323741,
						0
					],
					[
						25683.4532374101,
						3,
						431.654676258993,
						0
					]
				],
				"mustHitSection": true
			},
			{
				"lengthInSteps": 16,
				"sectionNotes": [],
				"mustHitSection": true
			},
			{
				"lengthInSteps": 16,
				"sectionNotes": [
					[
						28057.5539568345,
						1,
						0,
						0
					],
					[
						28273.381294964,
						3,
						107.913669064748,
						0
					],
					[
						28705.035971223,
						3,
						107.913669064748,
						0
					],
					[
						28920.8633093525,
						0,
						107.913669064748,
						0
					],
					[
						27625.8992805755,
						1,
						107.913669064748,
						0
					]
				],
				"mustHitSection": false
			},
			{
				"lengthInSteps": 16,
				"sectionNotes": [
					[
						29568.345323741,
						1,
						107.913669064748,
						0
					],
					[
						30000,
						1,
						107.913669064748,
						0
					],
					[
						30215.8273381295,
						0,
						107.913669064748,
						0
					],
					[
						30647.4820143885,
						1,
						107.913669064748,
						0
					]
				],
				"mustHitSection": false
			},
			{
				"lengthInSteps": 16,
				"sectionNotes": [
					[
						31079.1366906475,
						2,
						323.741007194245,
						0
					],
					[
						31726.618705036,
						6,
						107.913669064748,
						0
					],
					[
						32158.273381295,
						7,
						107.913669064748,
						0
					],
					[
						32374.1007194245,
						5,
						107.913669064748,
						0
					],
					[
						32589.928057554,
						7,
						107.913669064748,
						0
					]
				],
				"mustHitSection": false
			},
			{
				"lengthInSteps": 16,
				"sectionNotes": [
					[
						32805.7553956835,
						0,
						755.395683453237,
						0
					]
				],
				"mustHitSection": true
			},
			{
				"lengthInSteps": 16,
				"sectionNotes": [
					[
						34964.0287769784,
						1,
						0
					],
					[
						35179.8561151079,
						3,
						107.913669064748
					],
					[
						35611.5107913669,
						3,
						107.913669064748
					],
					[
						36043.1654676259,
						1,
						107.913669064748
					],
					[
						34532.3741007194,
						1,
						107.913669064748
					]
				],
				"mustHitSection": true
			},
			{
				"lengthInSteps": 16,
				"sectionNotes": [
					[
						36474.8201438849,
						1,
						107.913669064748
					],
					[
						36906.4748201439,
						1,
						107.913669064748
					],
					[
						37553.9568345324,
						1,
						107.913669064748
					],
					[
						37769.7841726619,
						3,
						107.913669064748
					]
				],
				"mustHitSection": true
			},
			{
				"lengthInSteps": 16,
				"sectionNotes": [
					[
						37985.6115107914,
						2,
						323.741007194245
					],
					[
						38633.0935251799,
						6,
						107.913669064748,
						0
					],
					[
						38848.9208633094,
						4,
						107.913669064748,
						0
					],
					[
						39064.7482014389,
						7,
						107.913669064748,
						0
					],
					[
						39280.5755395684,
						5,
						107.913669064748,
						0
					],
					[
						39496.4028776979,
						7,
						107.913669064748,
						0
					]
				],
				"mustHitSection": true
			},
			{
				"lengthInSteps": 16,
				"sectionNotes": [
					[
						39712.2302158274,
						2,
						107.913669064748,
						0
					],
					[
						40143.8848920864,
						3,
						107.913669064748,
						0
					],
					[
						40359.7122302158,
						1,
						107.913669064748,
						0
					]
				],
				"mustHitSection": false
			},
			{
				"lengthInSteps": 16,
				"sectionNotes": [
					[
						42302.1582733813,
						2,
						107.913669064748,
						0
					],
					[
						42517.9856115108,
						3,
						107.913669064748,
						0
					],
					[
						42949.6402877698,
						0,
						107.913669064748,
						0
					],
					[
						41438.8489208633,
						0,
						107.913669064748,
						0
					],
					[
						41654.6762589928,
						3,
						107.913669064748,
						0
					]
				],
				"mustHitSection": false
			},
			{
				"lengthInSteps": 16,
				"sectionNotes": [
					[
						43165.4676258993,
						2,
						323.741007194245,
						0
					],
					[
						43597.1223021583,
						0,
						107.913669064748,
						0
					],
					[
						44028.7769784173,
						3,
						107.913669064748,
						0
					],
					[
						44244.6043165468,
						0,
						107.913669064748,
						0
					],
					[
						44676.2589928058,
						1,
						107.913669064748,
						0
					]
				],
				"mustHitSection": false
			},
			{
				"lengthInSteps": 16,
				"sectionNotes": [
					[
						44892.0863309353,
						2,
						107.913669064748,
						0
					],
					[
						45323.7410071943,
						0,
						107.913669064748,
						0
					],
					[
						45539.5683453238,
						3,
						107.913669064748,
						0
					],
					[
						45971.2230215828,
						3,
						0,
						0
					],
					[
						46079.1366906475,
						3,
						0,
						0
					],
					[
						46187.0503597123,
						3,
						107.913669064748,
						0
					],
					[
						46402.8776978418,
						2,
						107.913669064748,
						0
					]
				],
				"mustHitSection": false
			},
			{
				"lengthInSteps": 16,
				"sectionNotes": [
					[
						46618.7050359713,
						1,
						107.913669064748,
						0
					],
					[
						46834.5323741007,
						0,
						0,
						0
					],
					[
						47050.3597122302,
						0,
						107.913669064748,
						0
					],
					[
						47482.0143884892,
						3,
						107.913669064748,
						0
					],
					[
						47697.8417266187,
						2,
						0,
						0
					],
					[
						47913.6690647482,
						3,
						107.913669064748,
						0
					]
				],
				"mustHitSection": false
			},
			{
				"lengthInSteps": 16,
				"sectionNotes": [
					[
						49208.6330935252,
						2,
						107.913669064748
					],
					[
						49424.4604316547,
						3,
						107.913669064748
					],
					[
						49856.1151079137,
						0,
						107.913669064748
					],
					[
						48345.3237410072,
						0,
						107.913669064748
					],
					[
						48561.1510791367,
						3,
						107.913669064748
					]
				],
				"mustHitSection": true
			},
			{
				"lengthInSteps": 16,
				"sectionNotes": [
					[
						50071.9424460432,
						2,
						323.741007194245
					],
					[
						50503.5971223022,
						0,
						107.913669064748
					],
					[
						50935.2517985612,
						3,
						107.913669064748
					],
					[
						51151.0791366907,
						0,
						107.913669064748
					],
					[
						51582.7338129497,
						1,
						107.913669064748
					]
				],
				"mustHitSection": true
			},
			{
				"lengthInSteps": 16,
				"sectionNotes": [
					[
						51798.5611510792,
						2,
						107.913669064748
					],
					[
						52230.2158273382,
						0,
						107.913669064748
					],
					[
						52446.0431654677,
						3,
						107.913669064748
					],
					[
						52877.6978417267,
						3,
						0
					],
					[
						52985.6115107914,
						3,
						0
					],
					[
						53093.5251798562,
						3,
						107.913669064748
					],
					[
						53309.3525179857,
						2,
						107.913669064748
					]
				],
				"mustHitSection": true
			},
			{
				"lengthInSteps": 16,
				"sectionNotes": [
					[
						53525.1798561151,
						1,
						107.913669064748
					],
					[
						53741.0071942446,
						0,
						0
					],
					[
						53956.8345323741,
						0,
						107.913669064748
					],
					[
						54388.4892086331,
						3,
						107.913669064748
					],
					[
						54604.3165467626,
						2,
						0
					],
					[
						54820.1438848921,
						3,
						107.913669064748
					]
				],
				"mustHitSection": true
			},
			{
				"lengthInSteps": 16,
				"sectionNotes": [
					[
						55683.4532374101,
						2,
						107.913669064748,
						0
					],
					[
						56115.1079136691,
						1,
						107.913669064748,
						0
					],
					[
						56762.5899280576,
						0,
						0,
						0
					],
					[
						56546.7625899281,
						2,
						107.913669064748,
						0
					]
				],
				"mustHitSection": false
			},
			{
				"lengthInSteps": 16,
				"sectionNotes": [
					[
						57625.8992805756,
						3,
						0,
						0
					],
					[
						57841.7266187051,
						1,
						107.913669064748,
						0
					],
					[
						58273.3812949641,
						2,
						107.913669064748,
						0
					],
					[
						58489.2086330936,
						3,
						0,
						0
					],
					[
						56978.4172661871,
						1,
						107.913669064748,
						0
					],
					[
						57410.0719424461,
						0,
						107.913669064748,
						0
					]
				],
				"mustHitSection": false
			},
			{
				"lengthInSteps": 16,
				"sectionNotes": [
					[
						59136.690647482,
						2,
						107.913669064748
					],
					[
						59568.345323741,
						1,
						107.913669064748
					],
					[
						60215.8273381295,
						0,
						0
					],
					[
						60000,
						2,
						107.913669064748
					]
				],
				"mustHitSection": true
			},
			{
				"lengthInSteps": 16,
				"sectionNotes": [
					[
						61079.1366906475,
						3,
						0
					],
					[
						61294.964028777,
						1,
						107.913669064748
					],
					[
						61726.618705036,
						2,
						107.913669064748
					],
					[
						61942.4460431655,
						3,
						0
					],
					[
						60431.654676259,
						1,
						107.913669064748
					],
					[
						60863.309352518,
						0,
						107.913669064748
					]
				],
				"mustHitSection": true
			},
			{
				"lengthInSteps": 16,
				"sectionNotes": [
					[
						62158.273381295,
						3,
						0,
						0
					],
					[
						62374.1007194245,
						0,
						0,
						0
					],
					[
						62589.928057554,
						2,
						107.913669064748,
						0
					],
					[
						62805.7553956835,
						0,
						107.913669064748,
						0
					],
					[
						63237.4100719425,
						0,
						0,
						0
					],
					[
						63453.237410072,
						3,
						107.913669064748,
						0
					],
					[
						63669.0647482015,
						0,
						0,
						0
					]
				],
				"mustHitSection": false
			},
			{
				"lengthInSteps": 16,
				"sectionNotes": [
					[
						63884.892086331,
						0,
						107.913669064748,
						0
					],
					[
						64100.7194244605,
						1,
						0,
						0
					],
					[
						64316.54676259,
						3,
						107.913669064748,
						0
					],
					[
						64964.0287769785,
						1,
						0,
						0
					],
					[
						65395.6834532375,
						1,
						0,
						0
					]
				],
				"mustHitSection": false
			},
			{
				"lengthInSteps": 16,
				"sectionNotes": [
					[
						65611.5107913669,
						2,
						107.913669064748,
						0
					],
					[
						65827.3381294964,
						0,
						0,
						0
					],
					[
						66043.1654676259,
						1,
						107.913669064748,
						0
					],
					[
						66690.6474820144,
						1,
						0,
						0
					],
					[
						66906.4748201439,
						3,
						0,
						0
					],
					[
						67122.3021582734,
						2,
						0,
						0
					]
				],
				"mustHitSection": false
			},
			{
				"lengthInSteps": 16,
				"sectionNotes": [
					[
						67338.1294964029,
						0,
						107.913669064748,
						0
					],
					[
						67769.7841726619,
						0,
						107.913669064748,
						0
					],
					[
						67985.6115107914,
						1,
						0,
						0
					],
					[
						68201.4388489209,
						0,
						107.913669064748,
						0
					],
					[
						68633.0935251799,
						1,
						107.913669064748,
						0
					],
					[
						68848.9208633094,
						2,
						107.913669064748,
						0
					]
				],
				"mustHitSection": false
			},
			{
				"lengthInSteps": 16,
				"sectionNotes": [
					[
						69064.7482014389,
						3,
						0
					],
					[
						69280.5755395684,
						0,
						0
					],
					[
						69496.4028776979,
						2,
						107.913669064748
					],
					[
						69712.2302158274,
						0,
						107.913669064748
					],
					[
						70143.8848920864,
						0,
						0
					],
					[
						70359.7122302159,
						3,
						107.913669064748
					],
					[
						70575.5395683454,
						0,
						0
					],
					[
						70683.4532374101,
						2,
						0
					],
					[
						69064.7482014389,
						7,
						755.395683453237,
						0
					],
					[
						69928.0575539569,
						6,
						647.482014388489,
						0
					],
					[
						70359.7122302159,
						0,
						0,
						3
					]
				],
				"mustHitSection": true
			},
			{
				"lengthInSteps": 16,
				"sectionNotes": [
					[
						70791.3669064749,
						0,
						107.913669064748
					],
					[
						71007.1942446044,
						1,
						0
					],
					[
						71223.0215827339,
						3,
						107.913669064748
					],
					[
						71870.5035971223,
						1,
						0
					],
					[
						72302.1582733813,
						1,
						0
					],
					[
						70791.3669064749,
						4,
						755.395683453237,
						0
					],
					[
						71654.6762589929,
						5,
						755.395683453237,
						0
					]
				],
				"mustHitSection": true
			},
			{
				"lengthInSteps": 16,
				"sectionNotes": [
					[
						72517.9856115108,
						6,
						107.913669064748
					],
					[
						72841.7266187051,
						7,
						0
					],
					[
						72733.8129496403,
						4,
						0
					],
					[
						72949.6402877698,
						5,
						107.913669064748
					],
					[
						73597.1223021583,
						5,
						0
					],
					[
						73812.9496402878,
						7,
						0
					],
					[
						74028.7769784173,
						6,
						0
					],
					[
						72517.9856115108,
						3,
						1618.70503597122,
						0
					]
				],
				"mustHitSection": false
			},
			{
				"lengthInSteps": 16,
				"sectionNotes": [
					[
						74244.6043165468,
						4,
						107.913669064748
					],
					[
						74460.4316546763,
						7,
						0
					],
					[
						74676.2589928058,
						4,
						107.913669064748
					],
					[
						75107.9136690648,
						4,
						107.913669064748
					],
					[
						75539.5683453238,
						5,
						107.913669064748
					],
					[
						75323.7410071943,
						7,
						107.913669064748
					],
					[
						75755.3956834533,
						6,
						107.913669064748
					],
					[
						74244.6043165468,
						2,
						755.395683453237,
						0
					]
				],
				"mustHitSection": false
			},
			{
				"lengthInSteps": 16,
				"sectionNotes": [
					[
						76187.0503597123,
						1,
						0,
						0
					],
					[
						76402.8776978418,
						1,
						0,
						0
					],
					[
						75971.2230215828,
						1,
						0,
						0
					],
					[
						76834.5323741008,
						2,
						215.827338129496,
						0
					],
					[
						77158.273381295,
						3,
						107.913669064748,
						0
					],
					[
						77374.1007194245,
						0,
						107.913669064748,
						0
					],
					[
						75971.2230215828,
						4,
						755.395683453237,
						0
					],
					[
						76618.7050359713,
						1,
						0,
						0
					]
				],
				"mustHitSection": false
			},
			{
				"lengthInSteps": 16,
				"sectionNotes": [
					[
						77697.8417266188,
						1,
						215.827338129496,
						0
					],
					[
						78021.582733813,
						0,
						215.827338129496,
						0
					],
					[
						78345.3237410072,
						2,
						323.741007194245,
						0
					],
					[
						78776.9784172662,
						3,
						215.827338129496,
						0
					]
				],
				"mustHitSection": false
			},
			{
				"lengthInSteps": 16,
				"sectionNotes": [
					[
						79640.2877697842,
						1,
						0
					],
					[
						79856.1151079137,
						1,
						0
					],
					[
						79424.4604316547,
						1,
						0
					],
					[
						80287.7697841727,
						2,
						215.827338129496
					],
					[
						80611.510791367,
						3,
						107.913669064748
					],
					[
						80827.3381294965,
						0,
						107.913669064748
					],
					[
						80071.9424460432,
						1,
						0,
						0
					]
				],
				"mustHitSection": true
			},
			{
				"lengthInSteps": 16,
				"sectionNotes": [
					[
						81151.0791366907,
						1,
						215.827338129496
					],
					[
						81474.820143885,
						0,
						215.827338129496
					],
					[
						81798.5611510792,
						2,
						323.741007194245
					],
					[
						82230.2158273382,
						3,
						215.827338129496
					]
				],
				"mustHitSection": true
			},
			{
				"lengthInSteps": 16,
				"sectionNotes": [
					[
						83093.5251798562,
						1,
						0
					],
					[
						83201.4388489209,
						1,
						0
					],
					[
						83525.1798561152,
						1,
						0
					],
					[
						83309.3525179857,
						1,
						0
					],
					[
						82877.6978417267,
						1,
						0
					],
					[
						83633.0935251799,
						1,
						0
					],
					[
						83741.0071942447,
						2,
						215.827338129496
					],
					[
						84064.7482014389,
						3,
						107.913669064748
					],
					[
						84280.5755395684,
						0,
						107.913669064748
					]
				],
				"mustHitSection": false
			},
			{
				"lengthInSteps": 16,
				"sectionNotes": [
					[
						84604.3165467627,
						1,
						215.827338129496
					],
					[
						84928.0575539569,
						0,
						215.827338129496
					],
					[
						85251.7985611511,
						2,
						323.741007194245
					],
					[
						85683.4532374101,
						3,
						215.827338129496
					]
				],
				"mustHitSection": false
			},
			{
				"lengthInSteps": 16,
				"sectionNotes": [
					[
						86546.7625899281,
						1,
						0
					],
					[
						86654.6762589929,
						1,
						0
					],
					[
						86978.4172661871,
						1,
						0
					],
					[
						86762.5899280576,
						1,
						0
					],
					[
						86330.9352517986,
						1,
						0
					],
					[
						87086.3309352519,
						1,
						0
					],
					[
						87194.2446043166,
						2,
						215.827338129496
					],
					[
						87517.9856115109,
						3,
						107.913669064748
					],
					[
						87733.8129496404,
						0,
						107.913669064748
					],
					[
						87410.0719424461,
						1,
						0,
						3
					]
				],
				"mustHitSection": true
			},
			{
				"lengthInSteps": 16,
				"sectionNotes": [
					[
						88057.5539568346,
						1,
						215.827338129496
					],
					[
						88381.2949640288,
						0,
						215.827338129496
					],
					[
						88705.0359712231,
						2,
						323.741007194245
					],
					[
						89136.6906474821,
						3,
						539.568345323741,
						0
					]
				],
				"mustHitSection": true
			},
			{
				"lengthInSteps": 16,
				"sectionNotes": [
					[
						89784.1726618706,
						2,
						755.395683453237,
						0
					]
				],
				"mustHitSection": true
			},
			{
				"lengthInSteps": 16,
				"sectionNotes": [],
				"mustHitSection": true
			},
			{
				"lengthInSteps": 16,
				"sectionNotes": [],
				"mustHitSection": true
			},
			{
				"lengthInSteps": 16,
				"sectionNotes": [],
				"mustHitSection": true
			},
			{
				"lengthInSteps": 16,
				"sectionNotes": [
					[
						96906.474820144,
						3,
						107.913669064748,
						0
					],
					[
						97338.129496403,
						1,
						107.913669064748,
						0
					],
					[
						97553.9568345325,
						2,
						107.913669064748,
						0
					],
					[
						97769.784172662,
						0,
						107.913669064748,
						0
					],
					[
						98201.4388489209,
						1,
						107.913669064748,
						0
					],
					[
						97985.6115107914,
						2,
						107.913669064748,
						0
					]
				],
				"mustHitSection": false
			},
			{
				"lengthInSteps": 16,
				"sectionNotes": [
					[
						98525.1798561152,
						1,
						107.913669064748,
						0
					],
					[
						98848.9208633094,
						1,
						107.913669064748,
						0
					],
					[
						99064.7482014389,
						0,
						107.913669064748,
						0
					],
					[
						99280.5755395684,
						3,
						107.913669064748,
						0
					],
					[
						99712.2302158274,
						0,
						107.913669064748,
						0
					],
					[
						99928.0575539569,
						2,
						107.913669064748,
						0
					]
				],
				"mustHitSection": false
			},
			{
				"lengthInSteps": 16,
				"sectionNotes": [
					[
						100143.884892086,
						1,
						323.741007194245,
						0
					],
					[
						101438.848920863,
						7,
						215.827338129496,
						0
					]
				],
				"mustHitSection": false
			},
			{
				"lengthInSteps": 16,
				"sectionNotes": [
					[
						101870.503597122,
						0,
						755.395683453237,
						0
					],
					[
						102733.81294964,
						1,
						755.395683453237,
						0
					]
				],
				"mustHitSection": true
			},
			{
				"lengthInSteps": 16,
				"sectionNotes": [
					[
						103812.949640288,
						7,
						107.913669064748
					],
					[
						104244.604316547,
						5,
						107.913669064748
					],
					[
						104460.431654676,
						6,
						107.913669064748
					],
					[
						105107.913669065,
						5,
						107.913669064748
					],
					[
						104892.086330935,
						6,
						107.913669064748
					],
					[
						103812.949640288,
						3,
						107.913669064748
					],
					[
						104244.604316547,
						1,
						107.913669064748
					],
					[
						104460.431654676,
						2,
						107.913669064748
					],
					[
						105107.913669065,
						1,
						107.913669064748
					],
					[
						104892.086330935,
						2,
						107.913669064748
					]
				],
				"mustHitSection": true
			},
			{
				"lengthInSteps": 16,
				"sectionNotes": [
					[
						105431.654676259,
						5,
						107.913669064748
					],
					[
						105971.223021583,
						4,
						107.913669064748
					],
					[
						106187.050359712,
						7,
						107.913669064748
					],
					[
						106402.877697842,
						6,
						107.913669064748
					],
					[
						106834.532374101,
						6,
						107.913669064748
					],
					[
						105431.654676259,
						1,
						107.913669064748
					],
					[
						105755.395683453,
						1,
						107.913669064748
					],
					[
						105971.223021583,
						0,
						107.913669064748
					],
					[
						106187.050359712,
						3,
						107.913669064748
					],
					[
						106402.877697842,
						2,
						107.913669064748
					],
					[
						106834.532374101,
						2,
						107.913669064748
					],
					[
						105755.395683453,
						6,
						107.913669064748,
						0
					],
					[
						105755.395683453,
						3,
						0,
						3
					]
				],
				"mustHitSection": true
			},
			{
				"lengthInSteps": 16,
				"sectionNotes": [
					[
						108345.323741007,
						7,
						215.827338129496
					],
					[
						108669.064748202,
						6,
						0
					],
					[
						107050.35971223,
						2,
						107.913669064748,
						0
					],
					[
						107050.35971223,
						5,
						323.741007194245,
						0
					]
				],
				"mustHitSection": true
			},
			{
				"lengthInSteps": 16,
				"sectionNotes": [
					[
						108776.978417266,
						0,
						755.395683453237
					],
					[
						109640.287769784,
						1,
						755.395683453237
					]
				],
				"mustHitSection": false
			},
			{
				"lengthInSteps": 16,
				"sectionNotes": [
					[
						110503.597122302,
						2,
						755.395683453237,
						0
					],
					[
						111366.90647482,
						0,
						755.395683453237,
						0
					],
					[
						111366.90647482,
						5,
						755.395683453237,
						0
					]
				],
				"mustHitSection": false
			},
			{
				"lengthInSteps": 16,
				"sectionNotes": [
					[
						112230.215827338,
						7,
						539.568345323741,
						0
					],
					[
						112877.697841727,
						7,
						0,
						0
					],
					[
						113201.438848921,
						7,
						107.913669064748,
						0
					],
					[
						113417.26618705,
						5,
						215.827338129496,
						0
					],
					[
						113741.007194245,
						4,
						0,
						0
					],
					[
						112230.215827338,
						1,
						539.568345323741,
						0
					],
					[
						112877.697841727,
						1,
						0,
						0
					],
					[
						113201.438848921,
						3,
						107.913669064748,
						0
					],
					[
						113417.26618705,
						0,
						215.827338129496,
						0
					],
					[
						113741.007194245,
						3,
						0,
						0
					]
				],
				"mustHitSection": false
			},
			{
				"lengthInSteps": 16,
				"sectionNotes": [
					[
						113956.834532374,
						1,
						1618.70503597122,
						0
					],
					[
						113956.834532374,
						5,
						1618.70503597122,
						0
					]
				],
				"mustHitSection": true
			},
			{
				"lengthInSteps": 16,
				"sectionNotes": [
					[
						116978.417266187,
						2,
						0,
						0
					],
					[
						117194.244604317,
						3,
						0,
						0
					]
				],
				"mustHitSection": true
			},
			{
				"lengthInSteps": 16,
				"sectionNotes": [
					[
						117410.071942446,
						0,
						0,
						0
					],
					[
						117841.726618705,
						2,
						107.913669064748,
						0
					],
					[
						118057.553956835,
						1,
						107.913669064748,
						0
					],
					[
						118273.381294964,
						3,
						0,
						0
					],
					[
						118705.035971223,
						3,
						107.913669064748,
						0
					],
					[
						118920.863309353,
						2,
						107.913669064748,
						0
					],
					[
						117410.071942446,
						4,
						0,
						0
					],
					[
						117841.726618705,
						6,
						107.913669064748,
						0
					],
					[
						118057.553956835,
						5,
						107.913669064748,
						0
					],
					[
						118273.381294964,
						7,
						0,
						0
					],
					[
						118705.035971223,
						7,
						107.913669064748,
						0
					],
					[
						118920.863309353,
						6,
						107.913669064748,
						0
					]
				],
				"mustHitSection": true
			},
			{
				"lengthInSteps": 16,
				"sectionNotes": [
					[
						119352.517985612,
						3,
						0,
						0
					],
					[
						119568.345323741,
						0,
						107.913669064748,
						0
					],
					[
						119784.172661871,
						3,
						107.913669064748,
						0
					],
					[
						120323.741007194,
						3,
						215.827338129496,
						0
					],
					[
						120647.482014389,
						0,
						107.913669064748,
						0
					],
					[
						119352.517985612,
						7,
						0,
						0
					],
					[
						119568.345323741,
						4,
						107.913669064748,
						0
					],
					[
						119784.172661871,
						7,
						107.913669064748,
						0
					],
					[
						120323.741007194,
						4,
						215.827338129496,
						0
					],
					[
						120647.482014389,
						7,
						107.913669064748,
						0
					]
				],
				"mustHitSection": false
			},
			{
				"lengthInSteps": 16,
				"sectionNotes": [
					[
						120863.309352518,
						2,
						755.395683453237,
						0
					],
					[
						121726.618705036,
						3,
						539.568345323741,
						0
					],
					[
						120863.309352518,
						6,
						755.395683453237,
						0
					],
					[
						121726.618705036,
						5,
						539.568345323741,
						0
					],
					[
						122374.100719425,
						7,
						107.913669064748,
						0
					],
					[
						122374.100719425,
						0,
						539.568345323741,
						0
					]
				],
				"mustHitSection": true
			},
			{
				"lengthInSteps": 16,
				"sectionNotes": [],
				"mustHitSection": true
			},
			{
				"lengthInSteps": 16,
				"sectionNotes": [],
				"mustHitSection": true
			},
			{
				"lengthInSteps": 16,
				"sectionNotes": [],
				"mustHitSection": true
			},
			{
				"sectionNotes": [],
				"typeOfSection": 0,
				"lengthInSteps": 16,
				"altAnim": false,
				"mustHitSection": true,
				"changeBPM": false,
				"bpm": 165
			},
			{
				"sectionNotes": [],
				"typeOfSection": 0,
				"lengthInSteps": 16,
				"altAnim": false,
				"mustHitSection": true,
				"changeBPM": false,
				"bpm": 139
			},
			{
				"sectionNotes": [],
				"typeOfSection": 0,
				"lengthInSteps": 16,
				"altAnim": false,
				"mustHitSection": true,
				"changeBPM": false,
				"bpm": 139
			},
			{
				"sectionNotes": [],
				"typeOfSection": 0,
				"lengthInSteps": 16,
				"altAnim": false,
				"mustHitSection": true,
				"changeBPM": false,
				"bpm": 139
			},
			{
				"lengthInSteps": 16,
				"altAnim": false,
				"typeOfSection": 0,
				"sectionNotes": [],
				"bpm": 139,
				"changeBPM": false,
				"mustHitSection": true
			}
		],
		"player3": "gf",
		"song": "My Goal",
		"needsVoices": true,
		"validScore": true,
		"speed": 2.9,
		"bpm": 139
	}
}